Metadata-Version: 2.1
Name: blendr-cli
Version: 0.2.0
Summary: Blendr CLI tool for GPU Lending
Home-page: https://www.blendr.network
Author: Blendr Network
Author-email: tech@blendr.network
License: MIT
Keywords: blendr cli gpu lending
Requires-Dist: click ==8.1.7
Requires-Dist: requests ==2.31.0
Requires-Dist: colorama ==0.4.6
Requires-Dist: psutil ==5.9.8
Requires-Dist: python-socketio[client] ==5.11.2
Requires-Dist: keyring ==25.2.0
Requires-Dist: keyrings.alt ==5.0.1
Requires-Dist: speedtest-cli ==2.1.3
Requires-Dist: pandas ==2.2.2
Requires-Dist: transformers ==4.40.2
Requires-Dist: datasets ==2.19.1
Requires-Dist: py3nvml ==0.2.7
